chaosmagpy/__init__.py
chaosmagpy/chaos.py
chaosmagpy/config_utils.py
chaosmagpy/coordinate_utils.py
chaosmagpy/data_utils.py
chaosmagpy/model_utils.py
chaosmagpy/plot_utils.py
chaosmagpy/lib/Earth_conductivity.dat
chaosmagpy/lib/RC_index.h5
chaosmagpy/lib/frequency_spectrum_gsm.npz
chaosmagpy/lib/frequency_spectrum_sm.npz
chaosmagpy/lib/ne_110m_coastline.zip
chaosmagpy-0.14.dist-info/LICENSE
chaosmagpy-0.14.dist-info/METADATA
chaosmagpy-0.14.dist-info/WHEEL
chaosmagpy-0.14.dist-info/top_level.txt
chaosmagpy-0.14.dist-info/RECORD
