Metadata-Version: 2.1
Name: chaosmagpy
Version: 0.14
Summary: Evaluates the CHAOS geomagnetic field model and other models of Earth's magnetic field.
Author-email: Clemens Kloss <ancklo@space.dtu.dk>
Maintainer-email: Clemens Kloss <ancklo@space.dtu.dk>
License: 
Project-URL: Homepage, https://github.com/ancklo/ChaosMagPy
Project-URL: Documentation, https://chaosmagpy.readthedocs.io/en/
Project-URL: Repository, https://github.com/ancklo/ChaosMagPy.git
Project-URL: Issues, https://github.com/ancklo/ChaosMagPy/issues
Project-URL: Changelog, https://github.com/ancklo/ChaosMagPy/blob/master/CHANGELOG.rst
Keywords: CHAOS,geomagnetic field,spherical harmonics model,secular variation,core field,crustal field,magnetospheric field
Classifier: Intended Audience :: Science/Research
Classifier: License :: OSI Approved :: MIT License
Classifier: Operating System :: Unix
Classifier: Operating System :: POSIX
Classifier: Operating System :: Microsoft :: Windows
Classifier: Programming Language :: Python :: 3.6
Classifier: Programming Language :: Python :: 3.7
Classifier: Programming Language :: Python :: 3.8
Classifier: Programming Language :: Python :: 3.9
Classifier: Programming Language :: Python :: 3.10
Classifier: Programming Language :: Python :: 3.11
Classifier: Topic :: Scientific/Engineering :: Physics
Requires-Python: >=3.6
License-File: LICENSE
Requires-Dist: numpy <=1.26
Requires-Dist: scipy
Requires-Dist: pandas
Requires-Dist: Cython
Requires-Dist: h5py
Requires-Dist: pyshp >=2.3.1
Requires-Dist: hdf5storage >=0.1.17
Provides-Extra: full
Requires-Dist: matplotlib >=3.6 ; extra == 'full'
Requires-Dist: lxml >=4.3.4 ; extra == 'full'
